rhetorikos/__init__.py
rhetorikos/speak.py
rhetorikos-0.0.2.dist-info/LICENSE
rhetorikos-0.0.2.dist-info/METADATA
rhetorikos-0.0.2.dist-info/WHEEL
rhetorikos-0.0.2.dist-info/top_level.txt
rhetorikos-0.0.2.dist-info/RECORD
