Metadata-Version: 2.1
Name: rhetorikos
Version: 0.0.2
Summary: rhetorikos / ῥητορικός - ῥήτωρ (rhḗtōr, “public speaker”) + -ῐκός (-ikós)
Author-email: Alexander Fedotov <alex.fedotov@aol.com>
Project-URL: Homepage, https://github.com/rhetorikos/rhetorikos
Project-URL: Bug Tracker, https://github.com/rhetorikos/rhetorikos/issues
Classifier: Programming Language :: Python :: 3
Classifier: License :: OSI Approved :: MIT License
Classifier: Operating System :: OS Independent
Requires-Python: >=3.10
License-File: LICENSE
